{
  "schemaVersion": 1,
  "runId": "2026-04-28T21-14-17-624Z",
  "createdAt": "2026-04-28T21:14:17.624Z",
  "distribution": {
    "jobs": [
      {
        "jobId": 0,
        "tasks": [
          {
            "id": "CucumberTest",
            "duration": 10.495000000000001
          }
        ],
        "totalTime": 10.495000000000001
      },
      {
        "jobId": 1,
        "tasks": [],
        "totalTime": 0
      },
      {
        "jobId": 2,
        "tasks": [],
        "totalTime": 0
      },
      {
        "jobId": 3,
        "tasks": [],
        "totalTime": 0
      },
      {
        "jobId": 4,
        "tasks": [],
        "totalTime": 0
      },
      {
        "jobId": 5,
        "tasks": [],
        "totalTime": 0
      },
      {
        "jobId": 6,
        "tasks": [],
        "totalTime": 0
      },
      {
        "jobId": 7,
        "tasks": [],
        "totalTime": 0
      },
      {
        "jobId": 8,
        "tasks": [],
        "totalTime": 0
      },
      {
        "jobId": 9,
        "tasks": [],
        "totalTime": 0
      },
      {
        "jobId": 10,
        "tasks": [],
        "totalTime": 0
      },
      {
        "jobId": 11,
        "tasks": [],
        "totalTime": 0
      },
      {
        "jobId": 12,
        "tasks": [],
        "totalTime": 0
      },
      {
        "jobId": 13,
        "tasks": [],
        "totalTime": 0
      },
      {
        "jobId": 14,
        "tasks": [],
        "totalTime": 0
      },
      {
        "jobId": 15,
        "tasks": [],
        "totalTime": 0
      },
      {
        "jobId": 16,
        "tasks": [],
        "totalTime": 0
      },
      {
        "jobId": 17,
        "tasks": [],
        "totalTime": 0
      },
      {
        "jobId": 18,
        "tasks": [],
        "totalTime": 0
      },
      {
        "jobId": 19,
        "tasks": [],
        "totalTime": 0
      },
      {
        "jobId": 20,
        "tasks": [],
        "totalTime": 0
      },
      {
        "jobId": 21,
        "tasks": [],
        "totalTime": 0
      },
      {
        "jobId": 22,
        "tasks": [],
        "totalTime": 0
      },
      {
        "jobId": 23,
        "tasks": [],
        "totalTime": 0
      },
      {
        "jobId": 24,
        "tasks": [],
        "totalTime": 0
      },
      {
        "jobId": 25,
        "tasks": [],
        "totalTime": 0
      },
      {
        "jobId": 26,
        "tasks": [],
        "totalTime": 0
      },
      {
        "jobId": 27,
        "tasks": [],
        "totalTime": 0
      }
    ],
    "jobCount": 28,
    "totalDuration": 10.495000000000001,
    "metrics": {
      "criticalPath": 10.495000000000001,
      "minJobTime": 0,
      "idealJobTime": 0.3748214285714286,
      "balanceRatio": 28.000000000000004,
      "predictedSpeedUp": 1
    }
  }
}